hypeshed/common.py
hypeshed/trakt/__init__.py
hypeshed/trakt/common.py
hypeshed/trakt/headers.py
hypeshed/trakt/users.py
hypeshed-0.0.4.dist-info/LICENSE
hypeshed-0.0.4.dist-info/WHEEL
hypeshed-0.0.4.dist-info/METADATA
hypeshed-0.0.4.dist-info/RECORD
