Metadata-Version: 2.1
Name: hypeshed
Version: 0.0.4
Summary: A typestub package that defines types for public APIs
License: MIT
Author: Bence Nagy
Author-email: bence@underyx.me
Requires-Python: >=3.9,<4.0
Classifier: License :: OSI Approved :: MIT License
Classifier: Programming Language :: Python :: 3
Classifier: Programming Language :: Python :: 3.9
